.gitignore
CHANGES.txt
MANIFEST.in
README.txt
ez_setup.py
setup.py
AmFast.egg-info/PKG-INFO
AmFast.egg-info/SOURCES.txt
AmFast.egg-info/dependency_links.txt
AmFast.egg-info/requires.txt
AmFast.egg-info/top_level.txt
amfast/__init__.py
amfast/decoder.py
amfast/encoder.py
amfast/version.py
amfast/class_def/__init__.py
amfast/class_def/as_types.py
amfast/class_def/code_generator.py
amfast/class_def/django_class_def.py
amfast/class_def/sa_class_def.py
amfast/ext_src/amf.c
amfast/ext_src/amf.h
amfast/ext_src/buffer.c
amfast/ext_src/buffer.h
amfast/ext_src/context.c
amfast/ext_src/context.h
amfast/ext_src/decoder.c
amfast/ext_src/encoder.c
amfast/remoting/__init__.py
amfast/remoting/channel.py
amfast/remoting/cherrypy_channel.py
amfast/remoting/connection.py
amfast/remoting/connection_manager.py
amfast/remoting/django_channel.py
amfast/remoting/endpoint.py
amfast/remoting/flex_messages.py
amfast/remoting/gae_channel.py
amfast/remoting/gae_connection_manager.py
amfast/remoting/gae_subscription_manager.py
amfast/remoting/memcache_connection_manager.py
amfast/remoting/memcache_manager.py
amfast/remoting/memcache_subscription_manager.py
amfast/remoting/pyamf_converter.py
amfast/remoting/pyamf_endpoint.py
amfast/remoting/sa_connection_manager.py
amfast/remoting/sa_subscription_manager.py
amfast/remoting/subscription_manager.py
amfast/remoting/targets.py
amfast/remoting/thread_pool.py
amfast/remoting/tornado_channel.py
amfast/remoting/twisted_channel.py
amfast/remoting/wsgi_channel.py
client_lib/bin/AmFastLib.swc
client_lib/src/amfastlib/events/SaAttrEvent.as
client_lib/src/amfastlib/events/SaEvent.as
client_lib/src/amfastlib/models/SaObject.as
tests/__init__.py
tests/amf0_decoder_test.py
tests/amf0_encoder_test.py
tests/amf3_decoder_test.py
tests/amf3_encoder_test.py
tests/buffer_test.py
tests/connection_test.py
tests/context_test.py
tests/gae_test.py
tests/memory_test.py
tests/messaging_test.py
tests/remoting_test.py
tests/round_trip_test.py
tests/speed_test.py
tests/subscription_test.py