Metadata-Version: 1.0
Name: AmFast
Version: 0.5.3-r541
Summary: Flash remoting framework. Includes support for NetConnection, RemoteObject, IExternizeable, Flex Producer/Consumer messaging, custom type serialization, and a C-based AMF encoder/decoder.
Home-page: http://code.google.com/p/amfast/
Author: Dave Thompson
Author-email: dthomp325@gmail.com
License: UNKNOWN
Keywords: amf amf0 amf3 flash flex pyamf
Platform: any
Classifier: Programming Language :: Python :: 2.4
Classifier: Programming Language :: Python :: 2.5
Classifier: Programming Language :: Python :: 2.6
Classifier: Programming Language :: Python :: 2.7
Classifier: Development Status :: 5 - Production/Stable
Classifier: Intended Audience :: Developers
Classifier: License :: OSI Approved :: MIT License
Classifier: Topic :: Utilities
